balistoryanalyzer/__init__.py
balistoryanalyzer/aliasclustering/AliasClusteringRuleBased.py
balistoryanalyzer/aliasclustering/PairwiseDistanceString.py
balistoryanalyzer/aliasclustering/__init__.py
balistoryanalyzer/characterization/__init__.py
balistoryanalyzer/characterization/CoreferenceResolution/CoreferenceResolution.py
balistoryanalyzer/characterization/CoreferenceResolution/LinkedList.py
balistoryanalyzer/characterization/CoreferenceResolution/__init__.py
balistoryanalyzer/characterization/FeatureExtraction/BaseModelFeatureExtraction.py
balistoryanalyzer/characterization/FeatureExtraction/FeatureExtraction.py
balistoryanalyzer/characterization/FeatureExtraction/LexiconFeatureExtraction.py
balistoryanalyzer/characterization/FeatureExtraction/POSTagFeatureExtraction.py
balistoryanalyzer/characterization/FeatureExtraction/WordEmbeddingFeatureExtraction.py
balistoryanalyzer/characterization/FeatureExtraction/__init__.py
balistoryanalyzer/characterization/RuleBasedLexiconClassifier/RuleBasedLexiconClassifier.py
balistoryanalyzer/characterization/RuleBasedLexiconClassifier/__init__.py
balistoryanalyzer/characterization/SentenceGrouping/SentenceGrouping.py
balistoryanalyzer/characterization/SentenceGrouping/__init__.py
balistoryanalyzer/characterner/BaseModel.py
balistoryanalyzer/characterner/ConditionalRandomFields.py
balistoryanalyzer/characterner/HiddenMarkovModel.py
balistoryanalyzer/characterner/HybridBPSOCRF.py
balistoryanalyzer/characterner/ScikitLearnClassifiers.py
balistoryanalyzer/characterner/__init__.py
balistoryanalyzer/preparation/DataPreparation.py
balistoryanalyzer/preparation/__init__.py
balistoryanalyzer/pretrained_models/__init__.py
balistoryanalyzer/pretrained_models/characterner/LoadPretrainedModels.py
balistoryanalyzer/pretrained_models/characterner/__init__.py
balistoryanalyzer/pretrained_models/characterner/CRF_1/__init__.py
balistoryanalyzer/pretrained_models/characterner/CRF_1/pretrained_best_model.pkl
balistoryanalyzer-1.0.3.dist-info/LICENSE
balistoryanalyzer-1.0.3.dist-info/METADATA
balistoryanalyzer-1.0.3.dist-info/WHEEL
balistoryanalyzer-1.0.3.dist-info/top_level.txt
balistoryanalyzer-1.0.3.dist-info/RECORD
