Metadata-Version: 2.1
Name: balistoryanalyzer
Version: 1.0.3
Summary: A Python package for Balinese Narrative Text Analysis including but not limited to: balinese character named entity recognition, alias clustering, and characterization classification (protagonist vs antagonist)
Author: I Made Satria Bimantara
Author-email: satriabimantara.imd@gmail.com
Keywords: Balinese,NLP,Text Preprocessing,Narrative Text Analysis,Computational Linguistics
Classifier: Development Status :: 5 - Production/Stable
Classifier: Intended Audience :: Developers
Classifier: Intended Audience :: Science/Research
Classifier: License :: OSI Approved :: BSD License
Classifier: Programming Language :: Python :: 3
Classifier: Programming Language :: Python :: 3.8
Classifier: Operating System :: OS Independent
Classifier: Natural Language :: Indonesian
Classifier: Topic :: Text Processing :: Linguistic
Classifier: Topic :: Scientific/Engineering :: Artificial Intelligence
Requires-Python: >=3.8
License-File: LICENSE
Requires-Dist: pandas ==1.5.3
Requires-Dist: numpy ==1.24.2
Requires-Dist: balinese-library ==0.0.7
Requires-Dist: nltk ==3.9.1
Requires-Dist: openpyxl ==3.1.0
Requires-Dist: balinese-textpreprocessor ==1.0.5
Requires-Dist: hmmlearn ==0.3.0
Requires-Dist: scikit-learn ==1.2.1
Requires-Dist: scipy ==1.10.0
Requires-Dist: sklearn-crfsuite ==0.3.6
Requires-Dist: jaro-winkler ==2.0.3
Requires-Dist: distlib ==0.3.1
